{
  "message": "SUCCESS",
  "results": {
    "A구역": [
        {
            "day": 23,
            "progress": 5
        },
        {
            "day": 24,
            "progress": 9
        },
        {
            "day": 25,
            "progress": 13
        },
        {
            "day": 26,
            "progress": 18
        },
        {
            "day": 29,
            "progress": 50
        }
    ],
    "B구역": [
      {
          "day": 23,
          "progress": 10
      },
      {
          "day": 24,
          "progress": 15
      },
      {
          "day": 25,
          "progress": 30
      },
      {
          "day": 26,
          "progress": 18
      },
      {
          "day": 29,
          "progress": 50
      }
  ]
  }
  
}